src/dupper.py
dupper-0.1.2.dist-info/entry_points.txt
dupper-0.1.2.dist-info/LICENSE
dupper-0.1.2.dist-info/WHEEL
dupper-0.1.2.dist-info/METADATA
dupper-0.1.2.dist-info/RECORD
