Metadata-Version: 2.1
Name: dupper
Version: 0.1.2
Summary: 
License: MIT
Author: nixiesquid
Author-email: audu817@gmail.com
Requires-Python: >=3.8,<4.0
Classifier: License :: OSI Approved :: MIT License
Classifier: Programming Language :: Python :: 3
Classifier: Programming Language :: Python :: 3.8
Requires-Dist: fire (>=0.3.1,<0.4.0)
